qbase58/base58.c
qbase58/base58.h
qbase58/py_base58.cpython-311-x86_64-linux-musl.so
qbase58/__init__.py
qbase58/py_base58.c
qbase58/py_base58.pyi
qbase58-1.0.4.dist-info/METADATA
qbase58-1.0.4.dist-info/RECORD
qbase58-1.0.4.dist-info/top_level.txt
qbase58-1.0.4.dist-info/WHEEL
qbase58-1.0.4.dist-info/LICENSE
