Metadata-Version: 2.2
Name: qbase58
Version: 1.0.4
Summary: Quick Base58 encoding/decoding.
Home-page: https://github.com/qvecs/qbase58
Author: Quick Vectors
Author-email: felipe@qvecs.com
License: MIT
Project-URL: Bug Tracker, https://github.com/qvecs/qbase58/issues
Project-URL: Source Code, https://github.com/qvecs/qbase58
Classifier: Programming Language :: Python :: 3
Classifier: Programming Language :: C
Classifier: Programming Language :: Python :: Implementation :: CPython
Classifier: License :: OSI Approved :: MIT License
Classifier: Operating System :: OS Independent
Classifier: Topic :: Utilities
Requires-Python: >=3.8
License-File: LICENSE
Provides-Extra: dev
Requires-Dist: pytest; extra == "dev"
Dynamic: author
Dynamic: author-email
Dynamic: classifier
Dynamic: description
Dynamic: description-content-type
Dynamic: home-page
Dynamic: license
Dynamic: project-url
Dynamic: provides-extra
Dynamic: requires-python
Dynamic: summary
